.gitignore
LICENSE.txt
README.md
cleanup.sh
setup.cfg
setup.py
seclusion/__init__.py
seclusion.egg-info/PKG-INFO
seclusion.egg-info/SOURCES.txt
seclusion.egg-info/dependency_links.txt
seclusion.egg-info/top_level.txt