Metadata-Version: 1.1
Name: seclusion
Version: 1.1.0
Summary: A simple way to provide a secluded deployment location
Home-page: https://github.com/timpeoples/seclusion
Author: Tim Peoples
Author-email: pydev@toolman.org
License: GPL
Download-URL: https://github.com/timpeoples/seclusion/releases
Keywords: deployment,path,seclusion,dependencies
Platform: UNKNOWN
